pyqt_label_slider/__init__.py
pyqt_label_slider/labelSlider.py
pyqt_label_slider-0.0.1.dist-info/LICENSE
pyqt_label_slider-0.0.1.dist-info/METADATA
pyqt_label_slider-0.0.1.dist-info/WHEEL
pyqt_label_slider-0.0.1.dist-info/top_level.txt
pyqt_label_slider-0.0.1.dist-info/RECORD
