Metadata-Version: 2.1
Name: pyqt-label-slider
Version: 0.0.1
Summary: PyQt QSlider with QLabel(QLabel is on the left side, QSlider is on the right side, horizontal direction only) QLabel's value synchronizes with QSlider's value.
Home-page: https://github.com/yjg30737/pyqt-label-slider.git
Author: Jung Gyu Yoon
Author-email: yjg30737@gmail.com
License: MIT
Platform: UNKNOWN
License-File: LICENSE
Requires-Dist: PyQt5 (>=5.8)
